<?xml version="1.0" encoding="UTF-8"?>
<!DOCTYPE suite SYSTEM "http://testng.org/testng-1.0.dtd" >
<suite name="vallachSuite01">
  
    <test name="TestMethods">   
        <classes>
            <class name="dragos.DataProvidersExampleTest">
                <methods>
                    <include name="My First Test"/>
                    <include name="My Second Test"/>
                    <include name="My Third Test"/>
                </methods>
            </class>
        </classes>
    </test>
    
</suite>